{"_default": {"1": {"user": "gruffelf", "pass": "secret", "tasks": [{"name": "Another test ask", "category": "assess", "subject": "default", "description": "this is a test task this is a test task this is a test task this is a test task this is a test task this is a test task ", "date": "2014-12-31T00:00:00.000Z"}, {"name": "Study Maths", "category": "study", "subject": "default", "description": "", "date": null}, {"name": "task!!", "category": "study", "subject": "borgus", "description": "there is no escape there is no escape there is no escape there is no escape there is no escape there is no escape there is no escape there is no escape there is no escape there is no escape there is no escape ", "date": null}, {"name": "COGUS IS BONG", "category": "assess", "subject": "borgus", "description": "", "date": "2025-07-09T00:00:00.000Z"}, {"name": "b", "category": "study", "subject": "default", "description": "", "date": null}, {"name": "d", "category": "study", "subject": "default", "description": "", "date": null}, {"name": "fffffffffffffff fffffffffffffff ", "category": "assess", "subject": "default", "description": "", "date": "2025-07-10T00:00:00.000Z"}, {"name": "fffffffffffffff fffffffffffffff fffffffffffffff fffffffffffffff ", "category": "assess", "subject": "default", "description": "", "date": "2025-07-10T00:00:00.000Z"}], "subjects": ["borgus", "tingus"]}}}